[{"Regex": 1,"zearch": 2.533,"grep": 174.0,"ripgrep": 243.567,"hyperscan": 39.0,"zhs_lz4_p": 143.967,"zhs_zstd_p": 186.4,"zgrep_lz4_p": 300.233,"zgrep_zstd_p": 202.633,"zrg_lz4_p": 385.9,"zrg_zstd_p": 308.3,"Ignore": 0},{"Regex": 2,"zearch": 5.1,"grep": 410.367,"ripgrep": 680.0,"hyperscan": 212.933,"zhs_lz4_p": 395.3,"zhs_zstd_p": 507.033,"zgrep_lz4_p": 673.766,"zgrep_zstd_p": 472.866,"zrg_lz4_p": 970.7,"zrg_zstd_p": 805.167,"Ignore": 0},{"Regex": 3,"zearch": 7.733,"grep": 1004.967,"ripgrep": 1932.7,"hyperscan": 845.766,"zhs_lz4_p": 1055.1,"zhs_zstd_p": 1282.733,"zgrep_lz4_p": 1398.299,"zgrep_zstd_p": 1126.466,"zrg_lz4_p": 2070.4,"zrg_zstd_p": 1833.267,"Ignore": 0},{"Regex": 4,"zearch": 10.466,"grep": 1680.8,"ripgrep": 3252.967,"hyperscan": 1498.333,"zhs_lz4_p": 1729.0,"zhs_zstd_p": 2068.3,"zgrep_lz4_p": 2200.332,"zgrep_zstd_p": 1864.866,"zrg_lz4_p": 3224.133,"zrg_zstd_p": 2920.767,"Ignore": 0},{"Regex": 5,"zearch": 13.199,"grep": 2358.9,"ripgrep": 4591.367,"hyperscan": 2991.033,"zhs_lz4_p": 3243.533,"zhs_zstd_p": 3706.433,"zgrep_lz4_p": 3002.565,"zgrep_zstd_p": 2604.733,"zrg_lz4_p": 4441.7,"zrg_zstd_p": 4072.3,"Ignore": 0}]