[{"Regex": 1,"zearch": 106.7,"zgrep_lz4": 174.4,"zgrep_zstd": 272.3,"grep": 71.1,"zrg_zstd": 270.4,"zrg_lz4": 172.6,"ripgrep": 44.9,"Ignore": 0},{"Regex": 2,"zearch": 223.9,"zgrep_lz4": 377.1,"zgrep_zstd": 574.0,"grep": 172.4,"zrg_zstd": 565.9,"zrg_lz4": 368.1,"ripgrep": 113.9,"Ignore": 0},{"Regex": 3,"zearch": 343.5,"zgrep_lz4": 580.0,"zgrep_zstd": 876.7,"grep": 274.2,"zrg_zstd": 912.1,"zrg_lz4": 634.8,"ripgrep": 235.7,"Ignore": 0},{"Regex": 4,"zearch": 478.7,"zgrep_lz4": 784.7,"zgrep_zstd": 1181.7,"grep": 376.4,"zrg_zstd": 1464.6,"zrg_lz4": 1088.1,"ripgrep": 534.9,"Ignore": 0},{"Regex": 5,"zearch": 630.0,"zgrep_lz4": 1005.0,"zgrep_zstd": 1499.1,"grep": 496.1,"zrg_zstd": 2047.2,"zrg_lz4": 1573.4,"ripgrep": 876.1,"Ignore": 0},{"Regex": 6,"zearch": 784.9,"zgrep_lz4": 1235.1,"zgrep_zstd": 1826.4,"grep": 624.3,"zrg_zstd": 2696.9,"zrg_lz4": 2121.6,"ripgrep": 1272.0,"Ignore": 0},{"Regex": 7,"zearch": 940.5,"zgrep_lz4": 1559.8,"zgrep_zstd": 2250.6,"grep": 845.1,"zrg_zstd": 3352.0,"zrg_lz4": 2677.3,"ripgrep": 1676.1,"Ignore": 0},{"Regex": 8,"zearch": 1097.3,"zgrep_lz4": 1891.0,"zgrep_zstd": 2680.0,"grep": 1070.2,"zrg_zstd": 4016.3,"zrg_lz4": 3242.7,"ripgrep": 2088.8,"Ignore": 0},{"Regex": 9,"zearch": 1259.2,"zgrep_lz4": 2284.6,"zgrep_zstd": 3172.1,"grep": 1360.6,"zrg_zstd": 4949.2,"zrg_lz4": 4077.2,"ripgrep": 2762.0,"Ignore": 0},{"Regex": 10,"zearch": 1435.8,"zgrep_lz4": 2684.6,"zgrep_zstd": 3676.0,"grep": 1654.7,"zrg_zstd": 6014.6,"zrg_lz4": 5044.0,"ripgrep": 3572.9,"Ignore": 0}]