[
{
"Regex": "r1",
"zearch": {"avg": 59.033, "err": 0.345},
"zgrep_lz4_p": {"avg": 36.900, "err": 0.403},
"zgrep_zstd_p": {"avg": 44.300, "err": 0.770},
"grep": {"avg": 21.967, "err": 0.175},
"hyperscan": {"avg": 36.533, "err": 0.261},
"zhs_lz4_p": {"avg": 44.600, "err": 0.778},
"zhs_zstd_p": {"avg": 69.233, "err": 0.494},
"zrg_zstd_p": {"avg": 61.900, "err": 1.093},
"zrg_lz4_p": {"avg": 56.467, "err": 0.512},
"ripgrep": {"avg": 56.533, "err": 0.407},
"MatchesZ": 382418,
"MatchesGG": 382418,
"MatchesR": 382418,
"MatchesH": 382418
},
{
"Regex": "r2",
"zearch": {"avg": 54.000, "err": 0.297},
"zgrep_lz4_p": {"avg": 34.433, "err": 0.384},
"zgrep_zstd_p": {"avg": 44.333, "err": 0.626},
"grep": {"avg": 19.200, "err": 0.256},
"hyperscan": {"avg": 8.967, "err": 0.220},
"zhs_lz4_p": {"avg": 21.400, "err": 0.291},
"zhs_zstd_p": {"avg": 46.033, "err": 0.536},
"zrg_zstd_p": {"avg": 47.167, "err": 0.610},
"zrg_lz4_p": {"avg": 24.733, "err": 0.803},
"ripgrep": {"avg": 8.600, "err": 0.202},
"MatchesZ": 0,
"MatchesGG": 0,
"MatchesR": 0,
"MatchesH": 0
},
{
"Regex": "r3",
"zearch": {"avg": 59.267, "err": 0.387},
"zgrep_lz4_p": {"avg": 42.533, "err": 0.293},
"zgrep_zstd_p": {"avg": 44.367, "err": 0.493},
"grep": {"avg": 26.367, "err": 0.239},
"hyperscan": {"avg": 13.533, "err": 0.182},
"zhs_lz4_p": {"avg": 24.633, "err": 0.332},
"zhs_zstd_p": {"avg": 46.733, "err": 0.265},
"zrg_zstd_p": {"avg": 48.900, "err": 0.434},
"zrg_lz4_p": {"avg": 29.400, "err": 0.447},
"ripgrep": {"avg": 14.200, "err": 0.218},
"MatchesZ": 4522,
"MatchesGG": 4522,
"MatchesR": 4522,
"MatchesH": 4522
},
{
"Regex": "r4",
"zearch": {"avg": 59.900, "err": 0.317},
"zgrep_lz4_p": {"avg": 40.533, "err": 0.384},
"zgrep_zstd_p": {"avg": 44.933, "err": 0.740},
"grep": {"avg": 25.000, "err": 0.163},
"hyperscan": {"avg": 18.533, "err": 0.204},
"zhs_lz4_p": {"avg": 28.400, "err": 0.553},
"zhs_zstd_p": {"avg": 52.667, "err": 0.391},
"zrg_zstd_p": {"avg": 55.567, "err": 0.545},
"zrg_lz4_p": {"avg": 43.033, "err": 0.583},
"ripgrep": {"avg": 29.800, "err": 0.173},
"MatchesZ": 48227,
"MatchesGG": 48227,
"MatchesR": 48227,
"MatchesH": 48227
},
{
"Regex": "r5",
"zearch": {"avg": 72.633, "err": 0.725},
"zgrep_lz4_p": {"avg": 39.700, "err": 0.422},
"zgrep_zstd_p": {"avg": 44.800, "err": 0.898},
"grep": {"avg": 24.367, "err": 0.687},
"hyperscan": {"avg": 18.167, "err": 0.365},
"zhs_lz4_p": {"avg": 28.467, "err": 0.308},
"zhs_zstd_p": {"avg": 52.433, "err": 0.621},
"zrg_zstd_p": {"avg": 58.067, "err": 1.299},
"zrg_lz4_p": {"avg": 45.600, "err": 0.259},
"ripgrep": {"avg": 34.900, "err": 0.237},
"MatchesZ": 105880,
"MatchesGG": 105880,
"MatchesR": 105880,
"MatchesH": 105880
},
{
"Regex": "r6",
"zearch": {"avg": 95.667, "err": 0.626},
"zgrep_lz4_p": {"avg": 46.533, "err": 0.592},
"zgrep_zstd_p": {"avg": 45.633, "err": 1.451},
"grep": {"avg": 30.567, "err": 0.395},
"hyperscan": {"avg": 35.967, "err": 0.289},
"zhs_lz4_p": {"avg": 43.467, "err": 0.486},
"zhs_zstd_p": {"avg": 69.067, "err": 0.579},
"zrg_zstd_p": {"avg": 63.700, "err": 0.986},
"zrg_lz4_p": {"avg": 64.167, "err": 0.857},
"ripgrep": {"avg": 60.767, "err": 0.277},
"MatchesZ": 316241,
"MatchesGG": 316241,
"MatchesR": 316241,
"MatchesH": 316241
},
{
"Regex": "r7",
"zearch": {"avg": 61.167, "err": 0.610},
"zgrep_lz4_p": {"avg": 43.167, "err": 0.442},
"zgrep_zstd_p": {"avg": 45.367, "err": 1.122},
"grep": {"avg": 27.133, "err": 0.182},
"hyperscan": {"avg": 13.633, "err": 0.175},
"zhs_lz4_p": {"avg": 24.233, "err": 0.512},
"zhs_zstd_p": {"avg": 47.200, "err": 0.535},
"zrg_zstd_p": {"avg": 113.133, "err": 1.095},
"zrg_lz4_p": {"avg": 120.033, "err": 0.811},
"ripgrep": {"avg": 105.700, "err": 0.422},
"MatchesZ": 0,
"MatchesGG": 0,
"MatchesR": 0,
"MatchesH": 0
},
{
"Regex": "All",
"zstd": {"avg": 36.000, "err": 0.000},
"lz4": {"avg": 15.000, "err": 0.000},
"repair": {"avg": 152.000, "err": 0.000},
"gzip": {"avg": 96.000, "err": 0.000},
"zearch": {"avg": 65.952, "err": 1.801},
"grep": {"avg": 24.943, "err": 0.478},
"ripgrep": {"avg": 44.357, "err": 4.186},
"hyperscan": {"avg": 20.762, "err": 1.391},
"zhs_lz4_p": {"avg": 30.743, "err": 1.196},
"zhs_zstd_p": {"avg": 54.767, "err": 1.291},
"zgrep_lz4_p": {"avg": 40.543, "err": 0.532},
"zgrep_zstd_p": {"avg": 44.819, "err": 0.350},
"zrg_lz4_p": {"avg": 54.776, "err": 4.015},
"zrg_zstd_p": {"avg": 64.062, "err": 2.844}
}
]
