[{"Regex": 1,"zearch": 4.933,"grep": 4.367,"ripgrep": 4.767,"hyperscan": 4.967,"zhs_lz4_p": 5.833,"zhs_zstd_p": 7.433,"zgrep_lz4_p": 6.167,"zgrep_zstd_p": 6.767,"zrg_lz4_p": 5.8,"zrg_zstd_p": 6.967,"Ignore": 0},{"Regex": 2,"zearch": 9.933,"grep": 8.934,"ripgrep": 9.6,"hyperscan": 10.134,"zhs_lz4_p": 12.2,"zhs_zstd_p": 15.133,"zgrep_lz4_p": 12.367,"zgrep_zstd_p": 13.667,"zrg_lz4_p": 11.667,"zrg_zstd_p": 13.967,"Ignore": 0},{"Regex": 3,"zearch": 14.933,"grep": 13.534,"ripgrep": 14.467,"hyperscan": 15.367,"zhs_lz4_p": 18.767,"zhs_zstd_p": 23.066,"zgrep_lz4_p": 18.7,"zgrep_zstd_p": 20.634,"zrg_lz4_p": 17.534,"zrg_zstd_p": 21.067,"Ignore": 0},{"Regex": 4,"zearch": 19.933,"grep": 18.167,"ripgrep": 19.5,"hyperscan": 20.9,"zhs_lz4_p": 25.367,"zhs_zstd_p": 31.166,"zgrep_lz4_p": 25.4,"zgrep_zstd_p": 27.634,"zrg_lz4_p": 23.401,"zrg_zstd_p": 28.2,"Ignore": 0},{"Regex": 5,"zearch": 25.0,"grep": 23.0,"ripgrep": 27.067,"hyperscan": 26.533,"zhs_lz4_p": 32.2,"zhs_zstd_p": 39.466,"zgrep_lz4_p": 32.2,"zgrep_zstd_p": 34.767,"zrg_lz4_p": 31.501,"zrg_zstd_p": 36.767,"Ignore": 0},{"Regex": 6,"zearch": 30.167,"grep": 28.0,"ripgrep": 35.034,"hyperscan": 32.466,"zhs_lz4_p": 39.3,"zhs_zstd_p": 48.066,"zgrep_lz4_p": 39.1,"zgrep_zstd_p": 41.934,"zrg_lz4_p": 39.901,"zrg_zstd_p": 45.6,"Ignore": 0},{"Regex": 7,"zearch": 35.4,"grep": 33.2,"ripgrep": 43.167,"hyperscan": 38.999,"zhs_lz4_p": 46.833,"zhs_zstd_p": 57.266,"zgrep_lz4_p": 46.467,"zgrep_zstd_p": 49.367,"zrg_lz4_p": 48.701,"zrg_zstd_p": 54.667,"Ignore": 0},{"Regex": 8,"zearch": 40.7,"grep": 38.533,"ripgrep": 52.2,"hyperscan": 45.799,"zhs_lz4_p": 54.833,"zhs_zstd_p": 66.466,"zgrep_lz4_p": 53.867,"zgrep_zstd_p": 56.867,"zrg_lz4_p": 57.501,"zrg_zstd_p": 64.034,"Ignore": 0},{"Regex": 9,"zearch": 46.533,"grep": 43.933,"ripgrep": 62.233,"hyperscan": 52.966,"zhs_lz4_p": 63.333,"zhs_zstd_p": 76.533,"zgrep_lz4_p": 61.267,"zgrep_zstd_p": 64.434,"zrg_lz4_p": 67.168,"zrg_zstd_p": 74.001,"Ignore": 0},{"Regex": 10,"zearch": 52.533,"grep": 50.333,"ripgrep": 73.033,"hyperscan": 60.466,"zhs_lz4_p": 71.866,"zhs_zstd_p": 87.1,"zgrep_lz4_p": 69.634,"zgrep_zstd_p": 72.167,"zrg_lz4_p": 77.668,"zrg_zstd_p": 84.334,"Ignore": 0},{"Regex": 11,"zearch": 59.1,"grep": 57.2,"ripgrep": 88.0,"hyperscan": 68.299,"zhs_lz4_p": 80.866,"zhs_zstd_p": 97.667,"zgrep_lz4_p": 78.567,"zgrep_zstd_p": 80.9,"zrg_lz4_p": 93.668,"zrg_zstd_p": 100.301,"Ignore": 0},{"Regex": 12,"zearch": 65.733,"grep": 64.2,"ripgrep": 103.067,"hyperscan": 76.199,"zhs_lz4_p": 90.033,"zhs_zstd_p": 108.267,"zgrep_lz4_p": 87.7,"zgrep_zstd_p": 90.0,"zrg_lz4_p": 109.701,"zrg_zstd_p": 116.468,"Ignore": 0},{"Regex": 13,"zearch": 73.0,"grep": 71.567,"ripgrep": 118.8,"hyperscan": 84.266,"zhs_lz4_p": 99.433,"zhs_zstd_p": 119.0,"zgrep_lz4_p": 97.1,"zgrep_zstd_p": 99.267,"zrg_lz4_p": 125.768,"zrg_zstd_p": 132.635,"Ignore": 0}]