[
{
"Regex": "r1",
"zearch": {"avg": 1545.067, "err": 11.866},
"zgrep_lz4_p": {"avg": 789.633, "err": 7.558},
"zgrep_zstd_p": {"avg": 1084.433, "err": 7.093},
"grep": {"avg": 468.033, "err": 3.918},
"hyperscan": {"avg": 783.600, "err": 6.359},
"zhs_lz4_p": {"avg": 881.700, "err": 14.535},
"zhs_zstd_p": {"avg": 1648.267, "err": 16.188},
"zrg_zstd_p": {"avg": 1532.933, "err": 15.292},
"zrg_lz4_p": {"avg": 1276.733, "err": 6.779},
"ripgrep": {"avg": 1288.267, "err": 1.654},
"MatchesZ": 9562616,
"MatchesGG": 9562616,
"MatchesR": 9562616,
"MatchesH": 9562616
},
{
"Regex": "r2",
"zearch": {"avg": 1448.833, "err": 2.368},
"zgrep_lz4_p": {"avg": 710.333, "err": 6.453},
"zgrep_zstd_p": {"avg": 1071.467, "err": 2.577},
"grep": {"avg": 413.733, "err": 2.732},
"hyperscan": {"avg": 92.067, "err": 2.829},
"zhs_lz4_p": {"avg": 356.400, "err": 2.077},
"zhs_zstd_p": {"avg": 1040.333, "err": 3.726},
"zrg_zstd_p": {"avg": 1109.567, "err": 6.775},
"zrg_lz4_p": {"avg": 455.800, "err": 2.510},
"ripgrep": {"avg": 102.533, "err": 1.717},
"MatchesZ": 0,
"MatchesGG": 0,
"MatchesR": 0,
"MatchesH": 0
},
{
"Regex": "r3",
"zearch": {"avg": 1550.367, "err": 3.226},
"zgrep_lz4_p": {"avg": 915.100, "err": 7.587},
"zgrep_zstd_p": {"avg": 1128.233, "err": 16.956},
"grep": {"avg": 589.100, "err": 2.993},
"hyperscan": {"avg": 196.900, "err": 2.755},
"zhs_lz4_p": {"avg": 437.333, "err": 1.531},
"zhs_zstd_p": {"avg": 1073.633, "err": 12.096},
"zrg_zstd_p": {"avg": 1163.667, "err": 2.318},
"zrg_lz4_p": {"avg": 596.733, "err": 8.455},
"ripgrep": {"avg": 241.167, "err": 1.422},
"MatchesZ": 111170,
"MatchesGG": 111170,
"MatchesR": 111170,
"MatchesH": 111170
},
{
"Regex": "r4",
"zearch": {"avg": 1584.733, "err": 13.927},
"zgrep_lz4_p": {"avg": 875.033, "err": 4.104},
"zgrep_zstd_p": {"avg": 1108.533, "err": 17.231},
"grep": {"avg": 550.367, "err": 2.825},
"hyperscan": {"avg": 312.267, "err": 2.502},
"zhs_lz4_p": {"avg": 527.467, "err": 1.853},
"zhs_zstd_p": {"avg": 1215.200, "err": 13.625},
"zrg_zstd_p": {"avg": 1366.567, "err": 16.562},
"zrg_lz4_p": {"avg": 923.333, "err": 5.653},
"ripgrep": {"avg": 611.667, "err": 1.999},
"MatchesZ": 1204877,
"MatchesGG": 1204877,
"MatchesR": 1204877,
"MatchesH": 1204877
},
{
"Regex": "r5",
"zearch": {"avg": 1776.900, "err": 3.664},
"zgrep_lz4_p": {"avg": 843.900, "err": 5.021},
"zgrep_zstd_p": {"avg": 1089.200, "err": 8.623},
"grep": {"avg": 519.733, "err": 2.838},
"hyperscan": {"avg": 313.467, "err": 2.461},
"zhs_lz4_p": {"avg": 528.767, "err": 2.092},
"zhs_zstd_p": {"avg": 1225.733, "err": 14.894},
"zrg_zstd_p": {"avg": 1374.633, "err": 11.379},
"zrg_lz4_p": {"avg": 1007.567, "err": 4.142},
"ripgrep": {"avg": 752.967, "err": 1.582},
"MatchesZ": 2642415,
"MatchesGG": 2642415,
"MatchesR": 2642415,
"MatchesH": 2642415
},
{
"Regex": "r6",
"zearch": {"avg": 2181.733, "err": 6.743},
"zgrep_lz4_p": {"avg": 1014.067, "err": 7.448},
"zgrep_zstd_p": {"avg": 1150.367, "err": 17.131},
"grep": {"avg": 679.400, "err": 3.255},
"hyperscan": {"avg": 760.833, "err": 4.447},
"zhs_lz4_p": {"avg": 863.000, "err": 2.275},
"zhs_zstd_p": {"avg": 1636.833, "err": 11.762},
"zrg_zstd_p": {"avg": 1629.533, "err": 6.413},
"zrg_lz4_p": {"avg": 1451.767, "err": 7.367},
"ripgrep": {"avg": 1395.633, "err": 1.451},
"MatchesZ": 7907329,
"MatchesGG": 7907329,
"MatchesR": 7907329,
"MatchesH": 7907329
},
{
"Regex": "r7",
"zearch": {"avg": 1601.400, "err": 22.764},
"zgrep_lz4_p": {"avg": 933.233, "err": 5.954},
"zgrep_zstd_p": {"avg": 1122.933, "err": 16.400},
"grep": {"avg": 604.167, "err": 2.516},
"hyperscan": {"avg": 180.033, "err": 2.716},
"zhs_lz4_p": {"avg": 422.467, "err": 1.452},
"zhs_zstd_p": {"avg": 1062.533, "err": 12.739},
"zrg_zstd_p": {"avg": 2702.700, "err": 12.088},
"zrg_lz4_p": {"avg": 2871.067, "err": 11.736},
"ripgrep": {"avg": 2511.800, "err": 1.588},
"MatchesZ": 0,
"MatchesGG": 0,
"MatchesR": 0,
"MatchesH": 0
},
{
"Regex": "All",
"zstd": {"avg": 882.333, "err": 0.000},
"lz4": {"avg": 251.333, "err": 0.000},
"repair": {"avg": 4396.000, "err": 0.000},
"gzip": {"avg": 2330.333, "err": 0.000},
"zearch": {"avg": 1669.862, "err": 31.217},
"grep": {"avg": 546.362, "err": 11.204},
"ripgrep": {"avg": 986.290, "err": 103.975},
"hyperscan": {"avg": 377.024, "err": 35.280},
"zhs_lz4_p": {"avg": 573.876, "err": 26.782},
"zhs_zstd_p": {"avg": 1271.790, "err": 33.425},
"zgrep_lz4_p": {"avg": 868.757, "err": 12.720},
"zgrep_zstd_p": {"avg": 1107.881, "err": 6.132},
"zrg_lz4_p": {"avg": 1226.143, "err": 101.080},
"zrg_zstd_p": {"avg": 1554.229, "err": 67.778}
}
]
