[{"Regex": 1,"zearch": 2.433,"grep": 2.433,"ripgrep": 4.133,"hyperscan": 4.1,"zhs_lz4_p": 4.367,"zhs_zstd_p": 4.5,"zgrep_lz4_p": 2.9,"zgrep_zstd_p": 3.0,"zrg_lz4_p": 4.7,"zrg_zstd_p": 4.433,"Ignore": 0},{"Regex": 2,"zearch": 5.133,"grep": 4.866,"ripgrep": 8.333,"hyperscan": 8.233,"zhs_lz4_p": 8.834,"zhs_zstd_p": 9.2,"zgrep_lz4_p": 5.833,"zgrep_zstd_p": 6.033,"zrg_lz4_p": 9.633,"zrg_zstd_p": 9.066,"Ignore": 0},{"Regex": 3,"zearch": 7.866,"grep": 7.333,"ripgrep": 12.6,"hyperscan": 12.4,"zhs_lz4_p": 13.567,"zhs_zstd_p": 14.0,"zgrep_lz4_p": 8.766,"zgrep_zstd_p": 9.2,"zrg_lz4_p": 14.6,"zrg_zstd_p": 13.799,"Ignore": 0},{"Regex": 4,"zearch": 10.666,"grep": 9.8,"ripgrep": 17.033,"hyperscan": 17.067,"zhs_lz4_p": 18.534,"zhs_zstd_p": 18.933,"zgrep_lz4_p": 11.766,"zgrep_zstd_p": 12.367,"zrg_lz4_p": 19.567,"zrg_zstd_p": 18.599,"Ignore": 0},{"Regex": 5,"zearch": 13.499,"grep": 12.5,"ripgrep": 21.633,"hyperscan": 21.967,"zhs_lz4_p": 23.901,"zhs_zstd_p": 24.166,"zgrep_lz4_p": 14.799,"zgrep_zstd_p": 15.534,"zrg_lz4_p": 24.7,"zrg_zstd_p": 23.632,"Ignore": 0},{"Regex": 6,"zearch": 16.332,"grep": 15.3,"ripgrep": 26.366,"hyperscan": 26.934,"zhs_lz4_p": 29.368,"zhs_zstd_p": 29.533,"zgrep_lz4_p": 17.832,"zgrep_zstd_p": 18.767,"zrg_lz4_p": 29.867,"zrg_zstd_p": 28.832,"Ignore": 0},{"Regex": 7,"zearch": 19.165,"grep": 18.133,"ripgrep": 31.499,"hyperscan": 32.101,"zhs_lz4_p": 34.935,"zhs_zstd_p": 35.166,"zgrep_lz4_p": 20.899,"zgrep_zstd_p": 22.0,"zrg_lz4_p": 35.467,"zrg_zstd_p": 34.099,"Ignore": 0},{"Regex": 8,"zearch": 22.032,"grep": 20.966,"ripgrep": 36.632,"hyperscan": 37.934,"zhs_lz4_p": 41.068,"zhs_zstd_p": 41.266,"zgrep_lz4_p": 23.999,"zgrep_zstd_p": 25.3,"zrg_lz4_p": 41.1,"zrg_zstd_p": 39.399,"Ignore": 0},{"Regex": 9,"zearch": 24.999,"grep": 23.833,"ripgrep": 41.799,"hyperscan": 50.867,"zhs_lz4_p": 54.568,"zhs_zstd_p": 54.533,"zgrep_lz4_p": 27.132,"zgrep_zstd_p": 28.6,"zrg_lz4_p": 46.8,"zrg_zstd_p": 44.866,"Ignore": 0},{"Regex": 10,"zearch": 28.032,"grep": 26.766,"ripgrep": 47.132,"hyperscan": 64.034,"zhs_lz4_p": 68.135,"zhs_zstd_p": 68.3,"zgrep_lz4_p": 30.365,"zgrep_zstd_p": 31.9,"zrg_lz4_p": 52.633,"zrg_zstd_p": 50.499,"Ignore": 0}]