[{"Regex": 1,"zearch": 2.6,"grep": 45.767,"ripgrep": 64.667,"hyperscan": 13.4,"zhs_lz4_p": 40.933,"zhs_zstd_p": 51.467,"zgrep_lz4_p": 79.267,"zgrep_zstd_p": 53.067,"zrg_lz4_p": 99.567,"zrg_zstd_p": 80.033,"Ignore": 0},{"Regex": 2,"zearch": 5.2,"grep": 107.467,"ripgrep": 177.3,"hyperscan": 61.7,"zhs_lz4_p": 109.1,"zhs_zstd_p": 136.067,"zgrep_lz4_p": 175.867,"zgrep_zstd_p": 123.367,"zrg_lz4_p": 248.1,"zrg_zstd_p": 207.933,"Ignore": 0},{"Regex": 3,"zearch": 7.867,"grep": 258.934,"ripgrep": 494.3,"hyperscan": 224.867,"zhs_lz4_p": 282.567,"zhs_zstd_p": 335.534,"zgrep_lz4_p": 360.134,"zgrep_zstd_p": 291.667,"zrg_lz4_p": 526.267,"zrg_zstd_p": 476.866,"Ignore": 0},{"Regex": 4,"zearch": 10.6,"grep": 430.367,"ripgrep": 828.4,"hyperscan": 391.134,"zhs_lz4_p": 457.467,"zhs_zstd_p": 536.934,"zgrep_lz4_p": 563.901,"zgrep_zstd_p": 479.234,"zrg_lz4_p": 818.534,"zrg_zstd_p": 752.299,"Ignore": 0},{"Regex": 5,"zearch": 13.4,"grep": 602.434,"ripgrep": 1167.1,"hyperscan": 767.067,"zhs_lz4_p": 842.934,"zhs_zstd_p": 952.301,"zgrep_lz4_p": 768.734,"zgrep_zstd_p": 668.467,"zrg_lz4_p": 1126.501,"zrg_zstd_p": 1043.399,"Ignore": 0}]