[{"Regex": 1,"zearch": 28.6,"grep": 10.433,"ripgrep": 6.233,"hyperscan": 6.333,"zhs_lz4_p": 13.733,"zhs_zstd_p": 24.7,"zgrep_lz4_p": 19.7,"zgrep_zstd_p": 22.667,"zrg_lz4_p": 14.433,"zrg_zstd_p": 24.833,"Ignore": 0},{"Regex": 2,"zearch": 59.9,"grep": 22.333,"ripgrep": 15.133,"hyperscan": 14.833,"zhs_lz4_p": 28.4,"zhs_zstd_p": 50.233,"zgrep_lz4_p": 40.667,"zgrep_zstd_p": 45.734,"zrg_lz4_p": 31.533,"zrg_zstd_p": 50.4,"Ignore": 0},{"Regex": 3,"zearch": 91.333,"grep": 34.933,"ripgrep": 31.833,"hyperscan": 23.933,"zhs_lz4_p": 43.9,"zhs_zstd_p": 76.5,"zgrep_lz4_p": 63.034,"zgrep_zstd_p": 68.834,"zrg_lz4_p": 55.366,"zrg_zstd_p": 80.167,"Ignore": 0},{"Regex": 4,"zearch": 122.833,"grep": 48.266,"ripgrep": 51.1,"hyperscan": 34.6,"zhs_lz4_p": 61.2,"zhs_zstd_p": 104.433,"zgrep_lz4_p": 85.901,"zgrep_zstd_p": 91.967,"zrg_lz4_p": 81.033,"zrg_zstd_p": 110.034,"Ignore": 0},{"Regex": 5,"zearch": 155.133,"grep": 62.566,"ripgrep": 81.233,"hyperscan": 45.933,"zhs_lz4_p": 78.567,"zhs_zstd_p": 133.4,"zgrep_lz4_p": 109.934,"zgrep_zstd_p": 115.4,"zrg_lz4_p": 112.2,"zrg_zstd_p": 142.401,"Ignore": 0},{"Regex": 6,"zearch": 193.766,"grep": 76.966,"ripgrep": 113.4,"hyperscan": 65.7,"zhs_lz4_p": 104.534,"zhs_zstd_p": 170.233,"zgrep_lz4_p": 134.134,"zgrep_zstd_p": 138.967,"zrg_lz4_p": 146.4,"zrg_zstd_p": 175.334,"Ignore": 0},{"Regex": 7,"zearch": 244.966,"grep": 92.999,"ripgrep": 167.967,"hyperscan": 85.5,"zhs_lz4_p": 130.567,"zhs_zstd_p": 207.333,"zgrep_lz4_p": 159.934,"zgrep_zstd_p": 162.7,"zrg_lz4_p": 209.9,"zrg_zstd_p": 234.801,"Ignore": 0}]