[{"Regex": 1,"zearch": 26.6,"grep": 7.767,"ripgrep": 6.633,"hyperscan": 6.733,"zhs_lz4_p": 13.767,"zhs_zstd_p": 22.933,"zgrep_lz4_p": 16.867,"zgrep_zstd_p": 20.6,"zrg_lz4_p": 15.033,"zrg_zstd_p": 23.533,"Ignore": 0},{"Regex": 2,"zearch": 53.5,"grep": 16.067,"ripgrep": 14.0,"hyperscan": 13.766,"zhs_lz4_p": 27.667,"zhs_zstd_p": 46.3,"zgrep_lz4_p": 34.534,"zgrep_zstd_p": 41.433,"zrg_lz4_p": 30.6,"zrg_zstd_p": 47.366,"Ignore": 0},{"Regex": 3,"zearch": 80.633,"grep": 25.034,"ripgrep": 22.067,"hyperscan": 21.533,"zhs_lz4_p": 41.767,"zhs_zstd_p": 70.0,"zgrep_lz4_p": 52.734,"zgrep_zstd_p": 62.333,"zrg_lz4_p": 46.933,"zrg_zstd_p": 71.233,"Ignore": 0},{"Regex": 4,"zearch": 107.866,"grep": 34.401,"ripgrep": 30.267,"hyperscan": 29.6,"zhs_lz4_p": 56.167,"zhs_zstd_p": 93.767,"zgrep_lz4_p": 71.534,"zgrep_zstd_p": 83.333,"zrg_lz4_p": 63.566,"zrg_zstd_p": 95.233,"Ignore": 0},{"Regex": 5,"zearch": 135.766,"grep": 44.001,"ripgrep": 41.8,"hyperscan": 37.767,"zhs_lz4_p": 70.634,"zhs_zstd_p": 117.534,"zgrep_lz4_p": 90.334,"zgrep_zstd_p": 104.333,"zrg_lz4_p": 83.166,"zrg_zstd_p": 120.6,"Ignore": 0},{"Regex": 6,"zearch": 164.366,"grep": 53.734,"ripgrep": 55.0,"hyperscan": 46.1,"zhs_lz4_p": 85.401,"zhs_zstd_p": 141.467,"zgrep_lz4_p": 109.367,"zgrep_zstd_p": 125.366,"zrg_lz4_p": 102.899,"zrg_zstd_p": 146.667,"Ignore": 0},{"Regex": 7,"zearch": 193.466,"grep": 64.001,"ripgrep": 71.9,"hyperscan": 55.133,"zhs_lz4_p": 100.568,"zhs_zstd_p": 166.167,"zgrep_lz4_p": 128.9,"zgrep_zstd_p": 146.466,"zrg_lz4_p": 124.632,"zrg_zstd_p": 172.9,"Ignore": 0},{"Regex": 8,"zearch": 222.866,"grep": 74.334,"ripgrep": 89.1,"hyperscan": 65.933,"zhs_lz4_p": 117.835,"zhs_zstd_p": 192.734,"zgrep_lz4_p": 148.9,"zgrep_zstd_p": 167.599,"zrg_lz4_p": 148.465,"zrg_zstd_p": 200.1,"Ignore": 0},{"Regex": 9,"zearch": 258.066,"grep": 84.834,"ripgrep": 107.833,"hyperscan": 77.433,"zhs_lz4_p": 135.202,"zhs_zstd_p": 219.934,"zgrep_lz4_p": 169.0,"zgrep_zstd_p": 188.732,"zrg_lz4_p": 172.498,"zrg_zstd_p": 227.533,"Ignore": 0},{"Regex": 10,"zearch": 294.666,"grep": 95.367,"ripgrep": 126.866,"hyperscan": 89.333,"zhs_lz4_p": 153.669,"zhs_zstd_p": 247.134,"zgrep_lz4_p": 189.133,"zgrep_zstd_p": 209.999,"zrg_lz4_p": 197.631,"zrg_zstd_p": 256.533,"Ignore": 0},{"Regex": 11,"zearch": 333.866,"grep": 108.567,"ripgrep": 156.466,"hyperscan": 101.333,"zhs_lz4_p": 172.269,"zhs_zstd_p": 274.867,"zgrep_lz4_p": 212.433,"zgrep_zstd_p": 231.866,"zrg_lz4_p": 232.531,"zrg_zstd_p": 288.633,"Ignore": 0},{"Regex": 12,"zearch": 376.799,"grep": 129.134,"ripgrep": 193.466,"hyperscan": 114.8,"zhs_lz4_p": 192.469,"zhs_zstd_p": 304.2,"zgrep_lz4_p": 242.633,"zgrep_zstd_p": 256.199,"zrg_lz4_p": 278.131,"zrg_zstd_p": 329.733,"Ignore": 0},{"Regex": 13,"zearch": 427.766,"grep": 149.734,"ripgrep": 230.466,"hyperscan": 132.767,"zhs_lz4_p": 217.002,"zhs_zstd_p": 338.1,"zgrep_lz4_p": 273.0,"zgrep_zstd_p": 281.099,"zrg_lz4_p": 323.931,"zrg_zstd_p": 371.6,"Ignore": 0}]